smmapdfs/__init__.py
smmapdfs/actions.py
smmapdfs/admin.py
smmapdfs/admin_abcs.py
smmapdfs/email.py
smmapdfs/tasks.py
smmapdfs/migrations/0001_initial.py
smmapdfs/migrations/0002_auto_20180611_1830.py
smmapdfs/migrations/0003_auto_20191126_1611.py
smmapdfs/migrations/__init__.py
smmapdfs/model_abcs/__init__.py
smmapdfs/model_abcs/pdfsandwich_abc.py
smmapdfs/model_abcs/pdfsandwich_field_abc.py
smmapdfs/models/__init__.py
smmapdfs/models/pdfsandwich_email.py
smmapdfs/models/pdfsandwich_font.py
smmapdfs/models/pdfsandwich_type.py
django_smmapdfs-1.2.0.dist-info/LICENSE
django_smmapdfs-1.2.0.dist-info/METADATA
django_smmapdfs-1.2.0.dist-info/WHEEL
django_smmapdfs-1.2.0.dist-info/top_level.txt
django_smmapdfs-1.2.0.dist-info/RECORD
