Metadata-Version: 2.1
Name: django-smmapdfs
Version: 1.2.0
Summary: Generate PDFs from django models by overlaying text onto an existing pdf
Home-page: https://github.com/auto-mat/smmapdfs
Author: Timothy Hobbs
Author-email: timothy.hobbs@auto-mat.cz
License: LPGL, see LICENSE file.
Download-URL: http://pypi.python.org/pypi/django-smmapdfs/
Platform: UNKNOWN
Classifier: Topic :: Utilities
Classifier: Natural Language :: English
Classifier: Operating System :: OS Independent
Classifier: Intended Audience :: Developers
Classifier: Environment :: Web Environment
Classifier: Framework :: Django
Classifier: Development Status :: 3 - Alpha
Classifier: Programming Language :: Python :: 3.3
Classifier: Programming Language :: Python :: 3.4
Classifier: Programming Language :: Python :: 3.5
Requires-Dist: django-colorfield
